Awz/Arsein.py
Awz/Clien.py
Awz/Copyright.py
Awz/Device.py
Awz/Encoder.py
Awz/Error.py
Awz/Getheader.py
Awz/GtM.py
Awz/PostData.py
Awz/TypeText.py
Awz/Zedcontent.py
Awz/__init__.py
awz-2.1.2.dist-info/LICENCE
awz-2.1.2.dist-info/METADATA
awz-2.1.2.dist-info/WHEEL
awz-2.1.2.dist-info/top_level.txt
awz-2.1.2.dist-info/RECORD
